{
    "5000": {
        "mm": [
            29948675.0,
            29868590.0,
            30070042.0,
            29778854.0,
            30054101.0,
            29950569.0,
            30095071.0,
            29963376.0,
            30072290.0,
            29871075,
            29866604.0,
            29977929.0,
            29933876.0,
            30138625.0,
            30030430
        ],
        "pm": [
            30504373.0,
            30415912.0,
            30095335.0,
            30244074.0,
            30284423.0,
            30284697.0,
            30172526.0,
            30285842.0,
            30294508.0,
            30153244.0,
            30247793.0,
            30305123.0,
            30352386.0,
            30277306.0,
            30115569.0
        ]
    },
    "10000": {
        "mm": [
            30070957.0,
            30061975.0,
            30167963.0,
            29822695,
            30319722.0,
            30181441.0,
            30232896.0,
            30233354.0,
            30317018.0,
            30050050.0,
            30005739.0,
            30102712,
            30254993.0,
            30283055.0,
            30163060.0
        ],
        "pm": [
            30752997.0,
            30727160.0,
            30444688.0,
            30471037.0,
            30504751.0,
            30452283.0,
            30409131.0,
            30528693.0,
            30504880.0,
            30478713.0,
            30487453.0,
            30479788.0,
            30516971.0,
            30401668.0,
            30319476.0
        ]
    },
    "25000": {
        "mm": [
            30610265.0,
            30353535.0,
            30429969.0,
            30286819.0,
            30528135.0,
            30553137.0,
            30504287.0,
            30434226.0,
            30604773.0,
            30460440.0,
            30427419,
            30369322.0,
            30463493.0,
            30525849.0,
            30412375.0
        ],
        "pm": [
            30863340.0,
            30817230.0,
            30627367.0,
            30697153.0,
            30724834.0,
            30675397.0,
            30621785.0,
            30661893.0,
            30693647.0,
            30719792.0,
            30714753.0,
            30844295,
            30688210.0,
            30512455.0,
            30732667
        ]
    },
    "50000": {
        "mm": [
            30638122.0,
            30398402.0,
            30694881.0,
            30476090.0,
            30674662.0,
            30583656.0,
            30687103.0,
            30453489.0,
            30708146.0,
            30572551.0,
            30476737.0,
            30610218.0,
            30591179.0,
            30602894.0,
            30594295.0
        ],
        "pm": [
            30863340.0,
            30940915.0,
            30782813.0,
            30728325.0,
            30758880.0,
            30741943.0,
            30769068.0,
            30830881.0,
            30712973.0,
            30780393.0,
            30828732.0,
            30878460.0,
            30754153.0,
            30582007.0,
            30806224
        ]
    }
}